{
  "done": true,
  "migration": {
    "name": "mig_d2e7p4fct945lrariktg",
    "operations": [
      {
        "add_column": {
          "table": "Books",
          "column": {
            "name": "startDate",
            "type": "timestamptz",
            "comment": "",
            "nullable": true
          }
        }
      }
    ]
  },
  "migrationType": "pgroll",
  "name": "mig_d2e7p4fct945lrariktg",
  "parent": "mig_d2e7ki8bs5avv4bj6dm0",
  "schema": "public",
  "startedAt": "2025-08-13T11:52:49.969776Z"
}
